gguf_cutter/__init__.py
gguf_cutter/__main__.py
gguf_cutter/downloader.py
gguf_cutter-0.0.4.dist-info/LICENSE
gguf_cutter-0.0.4.dist-info/WHEEL
gguf_cutter-0.0.4.dist-info/METADATA
gguf_cutter-0.0.4.dist-info/RECORD
