Metadata-Version: 2.1
Name: gguf-cutter
Version: 0.0.4
Summary: cutter/quantizor for gguf (bf/f16)
Author-email: calcuis <info@calcu.io>
Classifier: License :: OSI Approved :: MIT License
Requires-Dist: tqdm
Project-URL: Download, https://github.com/calcuis/gguf-quantizor/releases
Project-URL: GitHub, https://github.com/calcuis/gguf-quantizor
Project-URL: Homepage, https://gguf.org
Project-URL: Issues, https://github.com/calcuis/gguf-quantizor/issues
Project-URL: reddit, https://www.reddit.com/r/gguf
